PythonShujufenxiZhongwenBiji/README.md
PythonShujufenxiZhongwenBiji/__init__.py
PythonShujufenxiZhongwenBiji/__main__.py
PythonShujufenxiZhongwenBiji/file.epub
PythonShujufenxiZhongwenBiji/index.html
PythonShujufenxiZhongwenBiji/css/__init__.py
PythonShujufenxiZhongwenBiji/css/annotations.css
PythonShujufenxiZhongwenBiji/css/main.css
PythonShujufenxiZhongwenBiji/css/normalize.css
PythonShujufenxiZhongwenBiji/css/popup.css
PythonShujufenxiZhongwenBiji/font/__init__.py
PythonShujufenxiZhongwenBiji/font/fontello.eot
PythonShujufenxiZhongwenBiji/font/fontello.svg
PythonShujufenxiZhongwenBiji/font/fontello.ttf
PythonShujufenxiZhongwenBiji/font/fontello.woff
PythonShujufenxiZhongwenBiji/img/__init__.py
PythonShujufenxiZhongwenBiji/img/annotator-glyph-sprite.png
PythonShujufenxiZhongwenBiji/img/annotator-icon-sprite.png
PythonShujufenxiZhongwenBiji/img/apple-touch-icon.png
PythonShujufenxiZhongwenBiji/img/cancelfullscreen.png
PythonShujufenxiZhongwenBiji/img/close.png
PythonShujufenxiZhongwenBiji/img/fullscreen.png
PythonShujufenxiZhongwenBiji/img/loader.gif
PythonShujufenxiZhongwenBiji/img/menu-icon.png
PythonShujufenxiZhongwenBiji/img/save.png
PythonShujufenxiZhongwenBiji/img/saved.png
PythonShujufenxiZhongwenBiji/img/settings-s.png
PythonShujufenxiZhongwenBiji/img/settings.png
PythonShujufenxiZhongwenBiji/img/star.png
PythonShujufenxiZhongwenBiji/js/__init__.py
PythonShujufenxiZhongwenBiji/js/epub.js
PythonShujufenxiZhongwenBiji/js/epub.min.js
PythonShujufenxiZhongwenBiji/js/epub.min.map
PythonShujufenxiZhongwenBiji/js/hooks.min.js
PythonShujufenxiZhongwenBiji/js/hooks.min.map
PythonShujufenxiZhongwenBiji/js/reader.js
PythonShujufenxiZhongwenBiji/js/reader.js.map
PythonShujufenxiZhongwenBiji/js/reader.min.js
PythonShujufenxiZhongwenBiji/js/reader.min.map
PythonShujufenxiZhongwenBiji/js/hooks/__init__.py
PythonShujufenxiZhongwenBiji/js/hooks/extensions/__init__.py
PythonShujufenxiZhongwenBiji/js/hooks/extensions/highlight.js
python_shujufenxi_zhongwen_biji-2024.3.1.0.dist-info/METADATA
python_shujufenxi_zhongwen_biji-2024.3.1.0.dist-info/WHEEL
python_shujufenxi_zhongwen_biji-2024.3.1.0.dist-info/entry_points.txt
python_shujufenxi_zhongwen_biji-2024.3.1.0.dist-info/top_level.txt
python_shujufenxi_zhongwen_biji-2024.3.1.0.dist-info/RECORD
